easydjango/__init__.py
easydjango/cli.py
easydjango/project_setup.py
easydjango/settings_updater.py
easydjango/superuser_creator.py
easydjango/template_creator.py
easydjango/url_creator.py
easydjango/view_creator.py
easydjango_project-1.0.5.dist-info/LICENSE
easydjango_project-1.0.5.dist-info/METADATA
easydjango_project-1.0.5.dist-info/WHEEL
easydjango_project-1.0.5.dist-info/entry_points.txt
easydjango_project-1.0.5.dist-info/top_level.txt
easydjango_project-1.0.5.dist-info/RECORD
