Metadata-Version: 2.1
Name: easydjango-project
Version: 1.0.5
Summary: A CLI tool for quickly setting up Django projects.
Home-page: https://github.com/ghaithheni/easydjango
Author: Ghaith Heni
Author-email: elghaithheni@gmail.com
License: MIT
Classifier: Programming Language :: Python :: 3
Classifier: License :: OSI Approved :: MIT License
Classifier: Operating System :: OS Independent
Requires-Python: >=3.7
License-File: LICENSE
Requires-Dist: Django>=4.2
Requires-Dist: colorama
